consolepy/__init__.py
consolepy/console.py
consolepy-0.1.0.dist-info/METADATA
consolepy-0.1.0.dist-info/WHEEL
consolepy-0.1.0.dist-info/top_level.txt
consolepy-0.1.0.dist-info/RECORD
