Metadata-Version: 2.1
Name: consolepy
Version: 0.1.0
Summary: Una biblioteca para mostrar los mensajes por consola de una forma más estética
Author: Ángel David Vásquez Pedrozo
